capacho/VERSION
capacho/__init__.py
capacho/container.py
capacho/implementation_config.py
capacho/import_modules.py
capacho/interface.py
capacho/public_api.py
capacho/py.typed
capacho/register.py
capacho/register_callable.py
capacho/singleton.py
capacho/type_implementation_mapping.py
capacho-0.0.5.dist-info/METADATA
capacho-0.0.5.dist-info/WHEEL
capacho-0.0.5.dist-info/licenses/LICENSE
capacho-0.0.5.dist-info/RECORD
